pdflayoutxt/__init__.py
pdflayoutxt/main.py
pdflayoutxt/utils.py
pdflayoutxt-0.0.10.dist-info/LICENSE.txt
pdflayoutxt-0.0.10.dist-info/METADATA
pdflayoutxt-0.0.10.dist-info/WHEEL
pdflayoutxt-0.0.10.dist-info/top_level.txt
pdflayoutxt-0.0.10.dist-info/RECORD
